lcs_client/__init__.py
lcs_client-2.0.0.dist-info/LICENSE.txt
lcs_client-2.0.0.dist-info/METADATA
lcs_client-2.0.0.dist-info/WHEEL
lcs_client-2.0.0.dist-info/top_level.txt
lcs_client-2.0.0.dist-info/RECORD
