Metadata-Version: 2.1
Name: lcs-client
Version: 2.0.0
Summary: Client for interacting with LCS, the HackRU backend
Home-page: https://github.com/HackRU/python-lcs-client
Author: HackRU RnD
Author-email: rnd@hackru.org
License: MIT
Platform: UNKNOWN
Classifier: Development Status :: 4 - Beta
Classifier: Programming Language :: Python :: 3
Classifier: License :: OSI Approved :: MIT License
Requires-Dist: requests (>=2.0)
Provides-Extra: build
Requires-Dist: wheel (~=0.34) ; extra == 'build'
Requires-Dist: twine (~=3.2) ; extra == 'build'
Provides-Extra: dev
Requires-Dist: pytest (~=6.0) ; extra == 'dev'
Requires-Dist: pytest-mock (~=3.2) ; extra == 'dev'
Requires-Dist: pydoc-markdown (~=3.3) ; extra == 'dev'
